ptrade/__init__.py
ptrade/exception.py
ptrade/setup.py
ptrade/version.py
ptrade/cmdline/__init__.py
ptrade/cmdline/file/__init__.py
ptrade/cmdline/file/jupyter_content.ipynb
ptrade/cmdline/file/project/__init__.py
ptrade/cmdline/file/project/analysis.ipynb
ptrade/cmdline/file/project/rule.py
ptrade/cmdline/file/project/simulate.py
ptrade/cmdline/file/project/simulate_multiply.py
ptrade/component/__init__.py
ptrade/component/analysis.py
ptrade/component/order.py
ptrade/component/rule.py
ptrade/load/__init__.py
ptrade/simulate/__init__.py
ptrade/simulate/_property.py
ptrade/simulate/_record.py
ptrade/simulate/_shortcuts.py
ptrade/simulate/_trade.py
ptrade/simulate/simulate.py
ptrade/simulate/simulate_multiply.py
ptrade-1.0.5.dev13.dist-info/METADATA
ptrade-1.0.5.dev13.dist-info/WHEEL
ptrade-1.0.5.dev13.dist-info/entry_points.txt
ptrade-1.0.5.dev13.dist-info/top_level.txt
ptrade-1.0.5.dev13.dist-info/RECORD
